{"ENJfH9hcJc5KHy7jDnRVoA==":"sunset-3875295-1920-1920x1253.jpg","QBvTl86sJIi8IxyA4rlrWw==":"mbr-1368x912.jpg","yIakbvvEqVu+eFUhx/Z3kw==":"mbr-1920x1280.jpg","+zBFio9+r15eVe/7gUH2XQ==":"mbr-1920x1271.jpg","pI31QVCsngqU3P5sEezJeQ==":"mbr-1-1920x1271.jpg","aRV+DcezIllavpQL3eBqsA==":"mbr-1920x1440.jpg","0zjJmVZ1wh5konAXDSf+pg==":"mbr-1920x1203.jpg","DolSaGIWSEDE3T0pDOBJLQ==":"mbr-1-1920x1440.jpg","RBO+52J914RvMLSK4lzKCA==":"mbr-1-1920x1280.jpg","muoOUyT+x5lFsieOHsNAzg==":"mbr-1920x1762.jpg","32Ge1dNh5sxwOPsbsyOO4w==":"mbr-2-1920x1280.jpg","nnVZtfuLuv+zbqfripu2Xg==":"mbr-1920x1279.jpg","CHqxC0Xbs1CmGnqnEL5dVg==":"mbr-2-1920x1271.jpg","GIBYP2q8DRU/hqymNm2x4A==":"mbr-3-1920x1280.jpg","6Av4BUBFzdqrx7OCU15TFg==":"mbr-1600x1200.jpg","ckwhFBEsfCm+73h9XjFzUw==":"mbr-3-1920x1271.jpg","JWSgUDHlBCOnkHOJAZHhnQ==":"mbr-1920x1275.jpg","HEcHVdliHwDkrJXzKBzj+g==":"mbr-1271x1920.jpg","rXtg3ZsIBGf8lmHJxAwv9Q==":"mbr-1920x1232.jpg"}